visier_api_administration/__init__.py
visier_api_administration/py.typed
visier_api_administration/api/__init__.py
visier_api_administration/api/consolidated_analytics_api.py
visier_api_administration/api/email_domains_api.py
visier_api_administration/api/encryption_keys_api.py
visier_api_administration/api/network_subnets_api.py
visier_api_administration/api/permissions_api.py
visier_api_administration/api/production_versions_api.py
visier_api_administration/api/profiles_api.py
visier_api_administration/api/projects_api.py
visier_api_administration/api/release_version_configuration_api.py
visier_api_administration/api/sources_api.py
visier_api_administration/api/system_status_api.py
visier_api_administration/api/tenants_v1_api.py
visier_api_administration/api/tenants_v2_api.py
visier_api_administration/api/user_groups_v2_api.py
visier_api_administration/api/users_v1_api.py
visier_api_administration/api/users_v2_api.py
visier_api_administration/models/__init__.py
visier_api_administration/models/admin_all_tenants_status_apidto.py
visier_api_administration/models/admin_batch_tenant_provision_apidto.py
visier_api_administration/models/admin_business_location_dto.py
visier_api_administration/models/admin_consolidated_analytics_api_excluded_source_list_dto.py
visier_api_administration/models/admin_consolidated_analytics_api_source_tenant_list_dto.py
visier_api_administration/models/admin_consolidated_analytics_api_tenant_create_request_dto.py
visier_api_administration/models/admin_consolidated_analytics_api_tenant_list_response_dto.py
visier_api_administration/models/admin_consolidated_analytics_api_tenant_with_details.py
visier_api_administration/models/admin_consolidated_analytics_api_tenant_with_details_list_response_dto.py
visier_api_administration/models/admin_custom_property_dto.py
visier_api_administration/models/admin_custom_tenant_property_dto.py
visier_api_administration/models/admin_delete_user_group_v2_request.py
visier_api_administration-22222222.99201.1906.dist-info/METADATA
visier_api_administration-22222222.99201.1906.dist-info/WHEEL
visier_api_administration-22222222.99201.1906.dist-info/top_level.txt
visier_api_administration-22222222.99201.1906.dist-info/RECORD
